TheTwelveFactorAppZhongwenban/README.md
TheTwelveFactorAppZhongwenban/__init__.py
TheTwelveFactorAppZhongwenban/__main__.py
TheTwelveFactorAppZhongwenban/file.epub
TheTwelveFactorAppZhongwenban/index.html
TheTwelveFactorAppZhongwenban/css/__init__.py
TheTwelveFactorAppZhongwenban/css/annotations.css
TheTwelveFactorAppZhongwenban/css/main.css
TheTwelveFactorAppZhongwenban/css/normalize.css
TheTwelveFactorAppZhongwenban/css/popup.css
TheTwelveFactorAppZhongwenban/font/__init__.py
TheTwelveFactorAppZhongwenban/font/fontello.eot
TheTwelveFactorAppZhongwenban/font/fontello.svg
TheTwelveFactorAppZhongwenban/font/fontello.ttf
TheTwelveFactorAppZhongwenban/font/fontello.woff
TheTwelveFactorAppZhongwenban/img/__init__.py
TheTwelveFactorAppZhongwenban/img/annotator-glyph-sprite.png
TheTwelveFactorAppZhongwenban/img/annotator-icon-sprite.png
TheTwelveFactorAppZhongwenban/img/apple-touch-icon.png
TheTwelveFactorAppZhongwenban/img/cancelfullscreen.png
TheTwelveFactorAppZhongwenban/img/close.png
TheTwelveFactorAppZhongwenban/img/fullscreen.png
TheTwelveFactorAppZhongwenban/img/loader.gif
TheTwelveFactorAppZhongwenban/img/menu-icon.png
TheTwelveFactorAppZhongwenban/img/save.png
TheTwelveFactorAppZhongwenban/img/saved.png
TheTwelveFactorAppZhongwenban/img/settings-s.png
TheTwelveFactorAppZhongwenban/img/settings.png
TheTwelveFactorAppZhongwenban/img/star.png
TheTwelveFactorAppZhongwenban/js/__init__.py
TheTwelveFactorAppZhongwenban/js/epub.js
TheTwelveFactorAppZhongwenban/js/epub.min.js
TheTwelveFactorAppZhongwenban/js/epub.min.map
TheTwelveFactorAppZhongwenban/js/hooks.min.js
TheTwelveFactorAppZhongwenban/js/hooks.min.map
TheTwelveFactorAppZhongwenban/js/reader.js
TheTwelveFactorAppZhongwenban/js/reader.js.map
TheTwelveFactorAppZhongwenban/js/reader.min.js
TheTwelveFactorAppZhongwenban/js/reader.min.map
TheTwelveFactorAppZhongwenban/js/hooks/__init__.py
TheTwelveFactorAppZhongwenban/js/hooks/extensions/__init__.py
TheTwelveFactorAppZhongwenban/js/hooks/extensions/highlight.js
the_twelve_factor_app_zhongwenban-2024.3.2.0.dist-info/METADATA
the_twelve_factor_app_zhongwenban-2024.3.2.0.dist-info/WHEEL
the_twelve_factor_app_zhongwenban-2024.3.2.0.dist-info/entry_points.txt
the_twelve_factor_app_zhongwenban-2024.3.2.0.dist-info/top_level.txt
the_twelve_factor_app_zhongwenban-2024.3.2.0.dist-info/RECORD
